{
    "alicePrimary":"alicePrimary",
    "electron":"electron",
    "electronPrimary":"electronPrimary",
    "photon":"photon",
    "kaonFromPhi":"kaonFromPhi",
    "phiMeson":"phiMeson",
    "muon":"muon",
    "electronNOTfromTransport":"electronNOTfromTransport",
    "eFromNonpromptJpsi":"eFromNonpromptJpsi",
    "eFromPromptJpsi":"eFromPromptJpsi",
    "Jpsi":"Jpsi",
    "nonPromptJpsi":"nonPromptJpsi",
    "promptJpsi":"promptJpsi",
    "eFromNonpromptPsi2S":"eFromNonpromptPsi2S",
    "eFromPromptPsi2S":"eFromPromptPsi2S",
    "Psi2S":"Psi2S",
    "nonPromptPsi2S":"nonPromptPsi2S",
    "promptPsi2S":"promptPsi2S",
    "anyBeautyHadron":"anyBeautyHadron",
    "Bc":"Bc",
    "mumuFromJpsiFromBc":"mumuFromJpsiFromBc",
    "muFromBc":"muFromBc",
    "mumumuFromBc":"mumumuFromBc",
    "everythingFromBeauty":"everythingFromBeauty",
    "everythingFromEverythingFromBeauty":"everythingFromEverythingFromBeauty3",
    "allCharmHadrons":"allCharmHadrons",
    "allCharmFromBeauty":"allCharmFromBeauty",
    "allPromptCharm":"allPromptCharm",
    "electronFromPi0":"electronFromPi0",
    "Pi0decayTOe":"Pi0decayTOe",
    "Pi0":"Pi0",
    "LMeeLFQ":"LMeeLFQ",
    "LMeeLF":"LMeeLF",
    "electronFromDs":"electronFromDs",
    "dsMeson":"dsMeson",
    "electronFromPC":"electronFromPC",
    "dielectron":"dielectron",
    "dimuon":"dimuon",
    "electronMuonPair":"electronMuonPair",
    "dielectronFromPC":"dielectronFromPC",
    "dielectronPCPi0":"dielectronPCPi0",
    "eFromPi0":"eFromPi0",
    "eFromEta":"eFromEta",
    "eFromEtaPrime":"eFromEtaPrime",
    "eFromRho":"eFromRho",
    "eFromOmega":"eFromOmega",
    "eFromPhi":"eFromPhi",
    "eFromJpsi":"eFromJpsi",
    "muFromJpsi":"muFromJpsi",
    "eFromPsi2S":"eFromPsi2S",
    "muFromPsi2S":"muFromPsi2S",
    "eFromLMeeLFQ":"eFromLMeeLFQ",
    "LFQdecayToE":"LFQdecayToE",
    "eFromLMeeLF":"eFromLMeeLF",
    "eFromHc":"electronStandardQualityBenchmark",
    "eFromHb":"electronStandardQualityForO2MCdebug",
    "eFromMc":"eFromMc",
    "eFromMb":"eFromMb",
    "eFromBc":"eFromBc",
    "eFromBb":"eFromBb",
    "eFromPromptHc":"eFromPromptHc",
    "eFromNonPromptHc":"eFromNonPromptHc",
    "eeFromPi0":"eeFromPi0",
    "eeFromEta":"eeFromEta",
    "eeFromEtaprime":"eeFromEtaprime",
    "eeFromRho":"eeFromRho",
    "eeFromOmega":"eeFromOmega",
    "eeFromPhi":"eeFromPhi",
    "eeFromJpsi":"electronPIDnsigmaRandomized",
    "mumuFromJpsi":"mumuFromJpsi",
    "eeFromPsi2S":"eeFromPsi2S",
    "mumuFromPsi2S":"mumuFromPsi2S",
    "eeFromLMeeLFQ":"eeFromLMeeLFQ",
    "eeFromLMeeLF":"eeFromLMeeLF",
    "eeFromCC":"eeFromCC",
    "eeFromBB":"eeFromBB",
    "eeFromBtoC":"eeFromBtoC",
    "eeFromBandBtoC":"eeFromBandBtoC",
    "eeFromSingleBandBtoC":"eeFromSingleBandBtoC",
    "beautyPairs":"beautyPairs",
    "everythingFromBeautyPairs":"everythingFromBeautyPairs",
    "everythingFromEverythingFromBeautyPairsCM":"everythingFromEverythingFromBeautyPairsCM",
    "everythingFromBeautyANDeverythingFromEverythingFromBeautyPairs":"everythingFromBeautyANDeverythingFromEverythingFromBeautyPairs"
}